_squirrel.cpython-39-x86_64-linux-gnu.so
squirrel/__init__.py
squirrel_lang-0.2.1.dist-info/WHEEL
squirrel_lang-0.2.1.dist-info/METADATA
squirrel_lang-0.2.1.dist-info/RECORD
squirrel_lang-0.2.1.dist-info/top_level.txt
squirrel_lang-0.2.1.dist-info/licenses/LICENSE
