Metadata-Version: 2.4
Name: squirrel-lang
Version: 0.2.1
Summary: squirrel-lang - squirrel-lang vm machine, run squirrel-lang with python.
Home-page: https://github.com/shabbywu/squirrel-py
Author: shabbywu
Author-email: shabbywu@qq.com
Requires-Python: >=3.7
License-File: LICENSE
Provides-Extra: test
Requires-Dist: pytest; extra == "test"
Dynamic: author
Dynamic: author-email
Dynamic: description
Dynamic: home-page
Dynamic: license-file
Dynamic: provides-extra
Dynamic: requires-python
Dynamic: summary
